{"version":"1.5","timestamp":1702269927,"count":7,"index":{"":{"key":"","storage_key":"","template":null,"storage_timestamp":1698665592,"children":{"01.home":1698665592,"02.about":1698665592,"03.blog":1698665592},"checksum":"4ba1b977f17ca9a0201fcba3d455ba6c"},"01.home":{"key":"home","storage_key":"01.home","template":"default","storage_timestamp":1702269927,"markdown":{"":{"default":1702269927}},"checksum":"11f2faa174f23aad3cc56f8a64111abf"},"02.about":{"key":"about","storage_key":"02.about","template":"default","storage_timestamp":1702268948,"markdown":{"":{"default":1702268948}},"checksum":"81555cf7da8ab11c359e21eb42f96e2a"},"03.blog":{"key":"blog","storage_key":"03.blog","template":"blog","storage_timestamp":1702269847,"markdown":{"":{"blog":1699715180}},"children":{"01.apakah-itu-kecerdasan-buatan":1702269247,"02.post-two":1702269358,"03.komunitas-ai":1702269847},"checksum":"8d4d39fc92c49d733d0a9f01306e464b"},"03.blog\/01.apakah-itu-kecerdasan-buatan":{"key":"blog\/apakah-itu-kecerdasan-buatan","storage_key":"03.blog\/01.apakah-itu-kecerdasan-buatan","template":"default","storage_timestamp":1702269247,"markdown":{"":{"default":1702269247}},"checksum":"bc680045bc33e6bf2de8a9310d5e54e9"},"03.blog\/02.post-two":{"key":"blog\/post-two","storage_key":"03.blog\/02.post-two","template":"default","storage_timestamp":1702269358,"markdown":{"":{"default":1702269358}},"checksum":"b8338214029b3d07bfb560585035ac5f"},"03.blog\/03.komunitas-ai":{"key":"blog\/komunitas-ai","storage_key":"03.blog\/03.komunitas-ai","template":"default","storage_timestamp":1702269847,"markdown":{"":{"default":1702269810}},"checksum":"b067b807e5c35d344ab3e6d230b7e2c2"}}}